README.txt
deliverance.xml
paste.ini
run-flunc.sh
setup.py
test.ini
changes/changes.txt
changes/history.txt
changes/roadmap.txt
doc/dispatch.txt
ftests/_edit_page.twill
ftests/_go_before_page_created.twill
ftests/_go_existing_page.twill
ftests/_go_new_page.twill
ftests/_go_repo_future.twill
ftests/_go_unmodified_version.twill
ftests/find_nested_page.twill
ftests/find_page.twill
ftests/history.twill
ftests/svenweb.conf
ftests/svenweb.tsuite
svenweb/__init__.py
svenweb/convert.py
svenweb/edit.py
svenweb/factory.py
svenweb/lib.py
svenweb/template_loader.py
svenweb/webapp.py
svenweb.egg-info/PKG-INFO
svenweb.egg-info/SOURCES.txt
svenweb.egg-info/dependency_links.txt
svenweb.egg-info/entry_points.txt
svenweb.egg-info/not-zip-safe
svenweb.egg-info/requires.txt
svenweb.egg-info/top_level.txt
svenweb/middleware/__init__.py
svenweb/middleware/response/__init__.py
svenweb/middleware/response/setter/__init__.py
svenweb/middleware/response/setter/content_type.py
svenweb/read/__init__.py
svenweb/read/xformer.py
templates/edit.html
templates/history.atom
templates/history.html
templates/index.html
templates/view.html
www/welcome
www/.bzr/README
www/.bzr/branch-format
www/.bzr/branch/branch.conf
www/.bzr/branch/format
www/.bzr/branch/last-revision
www/.bzr/branch/tags
www/.bzr/checkout/conflicts
www/.bzr/checkout/dirstate
www/.bzr/checkout/format
www/.bzr/checkout/views
www/.bzr/repository/format
www/.bzr/repository/pack-names
www/.bzr/repository/indices/1691358956599b6977bfc13ba7149543.cix
www/.bzr/repository/indices/1691358956599b6977bfc13ba7149543.iix
www/.bzr/repository/indices/1691358956599b6977bfc13ba7149543.rix
www/.bzr/repository/indices/1691358956599b6977bfc13ba7149543.six
www/.bzr/repository/indices/1691358956599b6977bfc13ba7149543.tix
www/.bzr/repository/indices/3bf105c638011a67a49356d6dc54261b.cix
www/.bzr/repository/indices/3bf105c638011a67a49356d6dc54261b.iix
www/.bzr/repository/indices/3bf105c638011a67a49356d6dc54261b.rix
www/.bzr/repository/indices/3bf105c638011a67a49356d6dc54261b.six
www/.bzr/repository/indices/3bf105c638011a67a49356d6dc54261b.tix
www/.bzr/repository/indices/72aba1a90d94ba28b8d04028334f0d4e.cix
www/.bzr/repository/indices/72aba1a90d94ba28b8d04028334f0d4e.iix
