Metadata-Version: 1.0
Name: svenweb
Version: 0.6
Summary: web frontend to versioncontrolled document repository for read-write-index-history operations
Home-page: UNKNOWN
Author: Ethan Jucovy and Jeff Hammel
Author-email: ejucovy@gmail.com
License: GPLv3 or later
Platform: UNKNOWN
